{"/reset-styles.10131156717897.css":{"Content-Type":"text/css","Content-Encoding":"gzip","ETag":"10131156717897"},"/index.2441740788060.js":{"Content-Type":"application/javascript","Content-Encoding":"gzip","ETag":"2441740788060"},"/Font-Thin-IUOMN4HW.woff2":{"Content-Type":"font/woff2","Content-Encoding":"gzip","ETag":"9356730973845"},"/Font-Thin-MUM7DYQ7.woff":{"Content-Type":"font/woff","Content-Encoding":"gzip","ETag":"1933455464769"},"/Font-ThinItalic-AB5RI7ZJ.woff2":{"Content-Type":"font/woff2","Content-Encoding":"gzip","ETag":"2819823712124"},"/Font-ThinItalic-EJHZVFCH.woff":{"Content-Type":"font/woff","Content-Encoding":"gzip","ETag":"14655175294561"},"/Font-ExtraLight-7GWURIUN.woff2":{"Content-Type":"font/woff2","Content-Encoding":"gzip","ETag":"15512913477820"},"/Font-ExtraLight-NWAWMDRT.woff":{"Content-Type":"font/woff","Content-Encoding":"gzip","ETag":"17071433479211"},"/Font-ExtraLightItalic-PQZLPTJA.woff2":{"Content-Type":"font/woff2","Content-Encoding":"gzip","ETag":"13673544241154"},"/Font-ExtraLightItalic-FWBUQSHN.woff":{"Content-Type":"font/woff","Content-Encoding":"gzip","ETag":"17364155068396"},"/Font-Light-A2X6COZL.woff2":{"Content-Type":"font/woff2","Content-Encoding":"gzip","ETag":"6607954081996"},"/Font-Light-MLEWPO6W.woff":{"Content-Type":"font/woff","Content-Encoding":"gzip","ETag":"15528837811192"},"/Font-LightItalic-H2HTNPOD.woff2":{"Content-Type":"font/woff2","Content-Encoding":"gzip","ETag":"11382525558170"},"/Font-LightItalic-6WN2CQOT.woff":{"Content-Type":"font/woff","Content-Encoding":"gzip","ETag":"3363304741363"},"/Font-Regular-U5F6TEU7.woff2":{"Content-Type":"font/woff2","Content-Encoding":"gzip","ETag":"4050513646442"},"/Font-Regular-CJMPZWTZ.woff":{"Content-Type":"font/woff","Content-Encoding":"gzip","ETag":"5826815728552"},"/Font-Italic-RQ2W3YOO.woff2":{"Content-Type":"font/woff2","Content-Encoding":"gzip","ETag":"8832598806785"},"/Font-Italic-PXIDFCKV.woff":{"Content-Type":"font/woff","Content-Encoding":"gzip","ETag":"10077560993727"},"/Font-Medium-RNI73PYA.woff2":{"Content-Type":"font/woff2","Content-Encoding":"gzip","ETag":"114419177332"},"/Font-Medium-R35QKO2F.woff":{"Content-Type":"font/woff","Content-Encoding":"gzip","ETag":"1994745246616"},"/Font-MediumItalic-EXQWR2LS.woff2":{"Content-Type":"font/woff2","Content-Encoding":"gzip","ETag":"11832519966753"},"/Font-MediumItalic-AVX2526N.woff":{"Content-Type":"font/woff","Content-Encoding":"gzip","ETag":"6330889483532"},"/Font-SemiBold-7ZIMHKJU.woff2":{"Content-Type":"font/woff2","Content-Encoding":"gzip","ETag":"9004619498060"},"/Font-SemiBold-7BWDFOQP.woff":{"Content-Type":"font/woff","Content-Encoding":"gzip","ETag":"2702547949763"},"/Font-SemiBoldItalic-HTKDDYVI.woff2":{"Content-Type":"font/woff2","Content-Encoding":"gzip","ETag":"15482029466916"},"/Font-SemiBoldItalic-B4AHTHZ7.woff":{"Content-Type":"font/woff","Content-Encoding":"gzip","ETag":"6978235642267"},"/Font-Bold-FINJV4KU.woff2":{"Content-Type":"font/woff2","Content-Encoding":"gzip","ETag":"13505506313405"},"/Font-Bold-ZN4TVV5P.woff":{"Content-Type":"font/woff","Content-Encoding":"gzip","ETag":"9740472505880"},"/Font-BoldItalic-O52UQICD.woff2":{"Content-Type":"font/woff2","Content-Encoding":"gzip","ETag":"11410574928407"},"/Font-BoldItalic-CV5SJ4GZ.woff":{"Content-Type":"font/woff","Content-Encoding":"gzip","ETag":"11948336519754"},"/Font-ExtraBold-6VXKNDPB.woff2":{"Content-Type":"font/woff2","Content-Encoding":"gzip","ETag":"4928698825126"},"/Font-ExtraBold-D6P5HPRZ.woff":{"Content-Type":"font/woff","Content-Encoding":"gzip","ETag":"6567982827479"},"/Font-ExtraBoldItalic-3ILV4YNS.woff2":{"Content-Type":"font/woff2","Content-Encoding":"gzip","ETag":"14105545139582"},"/Font-ExtraBoldItalic-QSPC7RBG.woff":{"Content-Type":"font/woff","Content-Encoding":"gzip","ETag":"12179570325637"},"/Font-Black-PCIUJ5K5.woff2":{"Content-Type":"font/woff2","Content-Encoding":"gzip","ETag":"13515367681590"},"/Font-Black-GF2EZZQM.woff":{"Content-Type":"font/woff","Content-Encoding":"gzip","ETag":"7571844359334"},"/Font-BlackItalic-S7JBKCTE.woff2":{"Content-Type":"font/woff2","Content-Encoding":"gzip","ETag":"2037402822393"},"/Font-BlackItalic-X3SGNBCK.woff":{"Content-Type":"font/woff","Content-Encoding":"gzip","ETag":"7533410880928"},"/index.9230894624749.css":{"Content-Type":"text/css","Content-Encoding":"gzip","ETag":"9230894624749"}}
